pyrolib/__init__.py
pyrolib/cli_fuelmap.py
pyrolib/cli_post.py
pyrolib/__pycache__/__init__.cpython-310.pyc
pyrolib/__pycache__/cli_fuelmap.cpython-310.pyc
pyrolib/__pycache__/cli_post.cpython-310.pyc
pyrolib/blaze/__init__.py
pyrolib/blaze/subgrid_burning_area.py
pyrolib/blaze/__pycache__/__init__.cpython-310.pyc
pyrolib/blaze/__pycache__/subgrid_burning_area.cpython-310.pyc
pyrolib/data/Default_MNH_namelist.yml
pyrolib/data/fuel_db/DefaultSA.yml
pyrolib/data/fuel_db/FireFluxI.yml
pyrolib/data_processing/__init__.py
pyrolib/data_processing/firefluxI.py
pyrolib/data_processing/__pycache__/__init__.cpython-310.pyc
pyrolib/data_processing/__pycache__/firefluxI.cpython-310.pyc
pyrolib/fuelmap/__init__.py
pyrolib/fuelmap/fuel_database.py
pyrolib/fuelmap/fuelmap.py
pyrolib/fuelmap/fuels.py
pyrolib/fuelmap/patch.py
pyrolib/fuelmap/utility.py
pyrolib/fuelmap/__pycache__/__init__.cpython-310.pyc
pyrolib/fuelmap/__pycache__/fuel_database.cpython-310.pyc
pyrolib/fuelmap/__pycache__/fuelmap.cpython-310.pyc
pyrolib/fuelmap/__pycache__/fuels.cpython-310.pyc
pyrolib/fuelmap/__pycache__/patch.cpython-310.pyc
pyrolib/fuelmap/__pycache__/utility.cpython-310.pyc
pyrolib-0.4.1.dist-info/LICENSE
pyrolib-0.4.1.dist-info/METADATA
pyrolib-0.4.1.dist-info/WHEEL
pyrolib-0.4.1.dist-info/entry_points.txt
pyrolib-0.4.1.dist-info/top_level.txt
pyrolib-0.4.1.dist-info/RECORD
