Metadata-Version: 2.1
Name: pyrolib
Version: 0.4.1
Summary: Python tools for MesoNH-Blaze model
Home-page: https://pypi.org/project/pyrolib/
Author: Aurélien Costes
Author-email: aurelien.costes31@gmail.com
Project-URL: Homepage, https://github.com/Aurel31/pyrolib/
Project-URL: Documentation, https://pyrolib.readthedocs.io/en/latest/
Keywords: Blaze fire model,Méso-NH
Classifier: Programming Language :: Python :: 3.8
Classifier: Programming Language :: Python :: 3.9
Classifier: Programming Language :: Python :: 3.10
Classifier: License :: OSI Approved :: MIT License
Requires-Python: >=3.8
License-File: LICENSE
Requires-Dist: numpy (<2.0)
Requires-Dist: netCDF4 (<2.0)
Requires-Dist: scipy (<2.0)
Requires-Dist: bresenham
Requires-Dist: PyYAML
Requires-Dist: f90nml
Requires-Dist: click
Provides-Extra: docs
Requires-Dist: myst-parser ; extra == 'docs'
Requires-Dist: sphinx-rtd-theme ; extra == 'docs'
Provides-Extra: tests
Requires-Dist: pytest ; extra == 'tests'
